[
    {
        "icon": "location",
        "title": "Расположение",
        "description": "Мы находимся в центре города. Удобно добираться из любой точки Краснодара"
    },
    {
        "icon": "parking",
        "title": "Парковка",
        "description": "Не нужно беспокоится, где припарковать свой автомобиль, все уже готово."
    },
    {
        "icon": "production",
        "title": "Производство",
        "description": "Собственная зуботехническая лаборатория, работающее для нас и <a href=\"/coop.html\">не только</a>!"
    },
    {
        "icon": "team",
        "title": "Команда",
        "description": "Огромный опыт, практика за рубежом, участие в конференциях."
    },
    {
        "icon": "comfort",
        "title": "Комфорт",
        "description": "Уютная клиника, безболезненный процесс, комфортная обстановка"
    }
]